FancyBrackets/__init__.py
FancyBrackets/brackets.py
FancyBrackets-0.0.1.dist-info/LICENSE
FancyBrackets-0.0.1.dist-info/METADATA
FancyBrackets-0.0.1.dist-info/WHEEL
FancyBrackets-0.0.1.dist-info/top_level.txt
FancyBrackets-0.0.1.dist-info/RECORD
