Metadata-Version: 2.1
Name: FancyBrackets
Version: 0.0.1
Summary: Python package to plot fancy brackets in Matplotlib.
Home-page: UNKNOWN
Author: Thomas Steindl
Author-email: thomas.steindl95@gmx.at
License: UNKNOWN
Platform: UNKNOWN
Requires-Python: >=3.6
